jtes/__init__.py
jtes/_score.py
jtes-1.0.1.dist-info/LICENSE
jtes-1.0.1.dist-info/METADATA
jtes-1.0.1.dist-info/WHEEL
jtes-1.0.1.dist-info/top_level.txt
jtes-1.0.1.dist-info/RECORD
