Metadata-Version: 2.1
Name: jtes
Version: 1.0.1
Summary: Implementation of the Jaccard Timespan Event Score
Home-page: https://github.com/deddiag/python-jtes
Author: Marc Wenninger
Author-email: pypi@walwe.de
License: UNKNOWN
Platform: UNKNOWN
Classifier: Programming Language :: Python :: 3
Classifier: License :: OSI Approved :: MIT License
Classifier: Operating System :: OS Independent
Requires-Python: >=3.6
License-File: LICENSE
Requires-Dist: numpy
